{
  "forge_marker": 1,
  "defaults": {
    "textures": {
      "front": "ecotec:blocks/chronotyper_top",
      "back": "ecotec:blocks/chronotyper_top",
      "top": "ecotec:blocks/chronotyper_top",
      "bottom": "ecotec:blocks/chronotyper_top",
      "east": "ecotec:blocks/chronotyper_top",
      "west": "ecotec:blocks/chronotyper_top"
    },
    "uvlock": false,
    "model": "ecotec:machine"
  },
  "variants": {
    "facing":
    {
      "north": { },
      "south": { "y": 180 },
      "east": { "y": 90 },
      "west": { "y": 270 }
    },
    "inventory": [{ }]
  }
}